media_manager/__init__.py
media_manager/media_manager.py
media_manager/version.py
media_manager-0.75.25.dist-info/LICENSE
media_manager-0.75.25.dist-info/METADATA
media_manager-0.75.25.dist-info/WHEEL
media_manager-0.75.25.dist-info/entry_points.txt
media_manager-0.75.25.dist-info/top_level.txt
media_manager-0.75.25.dist-info/RECORD
