Metadata-Version: 2.1
Name: media-manager
Version: 0.75.25
Summary: Manage your media!
Home-page: https://github.com/Knuckles-Team/media-manager
Author: Audel Rouhi
Author-email: knucklessg1@gmail.com
License: MIT
Platform: UNKNOWN
Classifier: Development Status :: 5 - Production/Stable
Classifier: License :: Public Domain
Classifier: Environment :: Console
Classifier: Operating System :: POSIX :: Linux
Classifier: Programming Language :: Python :: 3.8
Classifier: Programming Language :: Python :: 3.9
Classifier: Programming Language :: Python :: 3.10
Classifier: Programming Language :: Python :: 3.11
Classifier: Programming Language :: Python :: 3.12
License-File: LICENSE
Requires-Dist: Pillow (>=10.2.0)
Requires-Dist: ffmpeg-python (>=0.2.0)
Provides-Extra: music
Requires-Dist: music-tag (>=0.4.3) ; extra == 'music'
Requires-Dist: shazamio (>=0.5.1) ; extra == 'music'
